{
  "main": {
    "kk": {
      "identity": {
        "version": {
          "_cldrVersion": "42"
        },
        "language": "kk"
      },
      "dates": {
        "fields": {
          "era": {
            "displayName": "дәуір"
          },
          "era-short": {
            "displayName": "дәуір"
          },
          "era-narrow": {
            "displayName": "дәуір"
          },
          "year": {
            "displayName": "жыл",
            "relative-type--1": "былтырғы жыл",
            "relative-type-0": "биылғы жыл",
            "relative-type-1": "келесі жыл",
            "relativeTime-type-future": {
              "relativeTimePattern-count-one": "{0} жылдан кейін",
              "relativeTimePattern-count-other": "{0} жылдан кейін"
            },
            "relativeTime-type-past": {
              "relativeTimePattern-count-one": "{0} жыл бұрын",
              "relativeTimePattern-count-other": "{0} жыл бұрын"
            }
          },
          "year-short": {
            "displayName": "ж.",
            "relative-type--1": "былтырғы жыл",
            "relative-type-0": "биылғы жыл",
            "relative-type-1": "келесі жыл",
            "relativeTime-type-future": {
              "relativeTimePattern-count-one": "{0} ж. кейін",
              "relativeTimePattern-count-other": "{0} ж. кейін"
            },
            "relativeTime-type-past": {
              "relativeTimePattern-count-one": "{0} ж. бұрын",
              "relativeTimePattern-count-other": "{0} ж. бұрын"
            }
          },
          "year-narrow": {
            "displayName": "ж.",
            "relative-type--1": "былтырғы жыл",
            "relative-type-0": "биылғы жыл",
            "relative-type-1": "келесі жыл",
            "relativeTime-type-future": {
              "relativeTimePattern-count-one": "{0} ж. кейін",
              "relativeTimePattern-count-other": "{0} ж. кейін"
            },
            "relativeTime-type-past": {
              "relativeTimePattern-count-one": "{0} ж. бұрын",
              "relativeTimePattern-count-other": "{0} ж. бұрын"
            }
          },
          "quarter": {
            "displayName": "ширек",
            "relative-type--1": "өткен тоқсан",
            "relative-type-0": "осы тоқсан",
            "relative-type-1": "келесі тоқсан",
            "relativeTime-type-future": {
              "relativeTimePattern-count-one": "{0} тоқсаннан кейін",
              "relativeTimePattern-count-other": "{0} тоқсаннан кейін"
            },
            "relativeTime-type-past": {
              "relativeTimePattern-count-one": "{0} тоқсан бұрын",
              "relativeTimePattern-count-other": "{0} тоқсан бұрын"
            }
          },
          "quarter-short": {
            "displayName": "ш.",
            "relative-type--1": "өткен тоқсан",
            "relative-type-0": "осы тоқсан",
            "relative-type-1": "келесі тоқсан",
            "relativeTime-type-future": {
              "relativeTimePattern-count-one": "{0} тқс. кейін",
              "relativeTimePattern-count-other": "{0} тқс. кейін"
            },
            "relativeTime-type-past": {
              "relativeTimePattern-count-one": "{0} тқс. бұрын",
              "relativeTimePattern-count-other": "{0} тқс. бұрын"
            }
          },
          "quarter-narrow": {
            "displayName": "ш.",
            "relative-type--1": "өткен тоқсан",
            "relative-type-0": "осы тоқсан",
            "relative-type-1": "келесі тоқсан",
            "relativeTime-type-future": {
              "relativeTimePattern-count-one": "{0} тқс. кейін",
              "relativeTimePattern-count-other": "{0} тқс. кейін"
            },
            "relativeTime-type-past": {
              "relativeTimePattern-count-one": "{0} тқс. бұрын",
              "relativeTimePattern-count-other": "{0} тқс. бұрын"
            }
          },
          "month": {
            "displayName": "ай",
            "relative-type--1": "өткен ай",
            "relative-type-0": "осы ай",
            "relative-type-1": "келесі ай",
            "relativeTime-type-future": {
              "relativeTimePattern-count-one": "{0} айдан кейін",
              "relativeTimePattern-count-other": "{0} айдан кейін"
            },
            "relativeTime-type-past": {
              "relativeTimePattern-count-one": "{0} ай бұрын",
              "relativeTimePattern-count-other": "{0} ай бұрын"
            }
          },
          "month-short": {
            "displayName": "ай",
            "relative-type--1": "өткен ай",
            "relative-type-0": "осы ай",
            "relative-type-1": "келесі ай",
            "relativeTime-type-future": {
              "relativeTimePattern-count-one": "{0} айдан кейін",
              "relativeTimePattern-count-other": "{0} айдан кейін"
            },
            "relativeTime-type-past": {
              "relativeTimePattern-count-one": "{0} ай бұрын",
              "relativeTimePattern-count-other": "{0} ай бұрын"
            }
          },
          "month-narrow": {
            "displayName": "ай",
            "relative-type--1": "өткен ай",
            "relative-type-0": "осы ай",
            "relative-type-1": "келесі ай",
            "relativeTime-type-future": {
              "relativeTimePattern-count-one": "{0} айдан кейін",
              "relativeTimePattern-count-other": "{0} айдан кейін"
            },
            "relativeTime-type-past": {
              "relativeTimePattern-count-one": "{0} ай бұрын",
              "relativeTimePattern-count-other": "{0} ай бұрын"
            }
          },
          "week": {
            "displayName": "апта",
            "relative-type--1": "өткен апта",
            "relative-type-0": "осы апта",
            "relative-type-1": "келесі апта",
            "relativeTime-type-future": {
              "relativeTimePattern-count-one": "{0} аптадан кейін",
              "relativeTimePattern-count-other": "{0} аптадан кейін"
            },
            "relativeTime-type-past": {
              "relativeTimePattern-count-one": "{0} апта бұрын",
              "relativeTimePattern-count-other": "{0} апта бұрын"
            },
            "relativePeriod": "{0} аптасы"
          },
          "week-short": {
            "displayName": "ап.",
            "relative-type--1": "өткен апта",
            "relative-type-0": "осы апта",
            "relative-type-1": "келесі апта",
            "relativeTime-type-future": {
              "relativeTimePattern-count-one": "{0} ап. кейін",
              "relativeTimePattern-count-other": "{0} ап. кейін"
            },
            "relativeTime-type-past": {
              "relativeTimePattern-count-one": "{0} ап. бұрын",
              "relativeTimePattern-count-other": "{0} ап. бұрын"
            },
            "relativePeriod": "{0} аптасы"
          },
          "week-narrow": {
            "displayName": "ап.",
            "relative-type--1": "өткен апта",
            "relative-type-0": "осы апта",
            "relative-type-1": "келесі апта",
            "relativeTime-type-future": {
              "relativeTimePattern-count-one": "{0} ап. кейін",
              "relativeTimePattern-count-other": "{0} ап. кейін"
            },
            "relativeTime-type-past": {
              "relativeTimePattern-count-one": "{0} ап. бұрын",
              "relativeTimePattern-count-other": "{0} ап. бұрын"
            },
            "relativePeriod": "{0} аптасы"
          },
          "weekOfMonth": {
            "displayName": "айдағы апта"
          },
          "weekOfMonth-short": {
            "displayName": "айдағы апта"
          },
          "weekOfMonth-narrow": {
            "displayName": "айдағы апта"
          },
          "day": {
            "displayName": "күн",
            "relative-type--2": "алдыңгүні",
            "relative-type--1": "кеше",
            "relative-type-0": "бүгін",
            "relative-type-1": "ертең",
            "relative-type-2": "бүрсігүні",
            "relativeTime-type-future": {
              "relativeTimePattern-count-one": "{0} күннен кейін",
              "relativeTimePattern-count-other": "{0} күннен кейін"
            },
            "relativeTime-type-past": {
              "relativeTimePattern-count-one": "{0} күн бұрын",
              "relativeTimePattern-count-other": "{0} күн бұрын"
            }
          },
          "day-short": {
            "displayName": "күн",
            "relative-type--2": "алдыңғы күні",
            "relative-type--1": "кеше",
            "relative-type-0": "бүгін",
            "relative-type-1": "ертең",
            "relative-type-2": "бүрсігүні",
            "relativeTime-type-future": {
              "relativeTimePattern-count-one": "{0} күннен кейін",
              "relativeTimePattern-count-other": "{0} күннен кейін"
            },
            "relativeTime-type-past": {
              "relativeTimePattern-count-one": "{0} күн бұрын",
              "relativeTimePattern-count-other": "{0} күн бұрын"
            }
          },
          "day-narrow": {
            "displayName": "күн",
            "relative-type--2": "алдыңғы күні",
            "relative-type--1": "кеше",
            "relative-type-0": "бүгін",
            "relative-type-1": "ертең",
            "relative-type-2": "бүрсігүні",
            "relativeTime-type-future": {
              "relativeTimePattern-count-one": "{0} күннен кейін",
              "relativeTimePattern-count-other": "{0} күннен кейін"
            },
            "relativeTime-type-past": {
              "relativeTimePattern-count-one": "{0} күн бұрын",
              "relativeTimePattern-count-other": "{0} күн бұрын"
            }
          },
          "dayOfYear": {
            "displayName": "жылдағы күн"
          },
          "dayOfYear-short": {
            "displayName": "жылдағы күн"
          },
          "dayOfYear-narrow": {
            "displayName": "жылдағы күн"
          },
          "weekday": {
            "displayName": "апта күні"
          },
          "weekday-short": {
            "displayName": "апта күні"
          },
          "weekday-narrow": {
            "displayName": "апта күні"
          },
          "weekdayOfMonth": {
            "displayName": "айдағы апта күні"
          },
          "weekdayOfMonth-short": {
            "displayName": "айдағы ап. күні"
          },
          "weekdayOfMonth-narrow": {
            "displayName": "айдағы ап. күні"
          },
          "sun": {
            "relative-type--1": "өткен жексенбі",
            "relative-type-0": "осы жексенбі",
            "relative-type-1": "келесі жексенбі",
            "relativeTime-type-future": {
              "relativeTimePattern-count-one": "{0} жексенбіден кейін",
              "relativeTimePattern-count-other": "{0} жексенбіден кейін"
            },
            "relativeTime-type-past": {
              "relativeTimePattern-count-one": "{0} жексенбі бұрын",
              "relativeTimePattern-count-other": "{0} жексенбі бұрын"
            }
          },
          "sun-short": {
            "relative-type--1": "өткен жек.",
            "relative-type-0": "осы жек.",
            "relative-type-1": "келесі жек.",
            "relativeTime-type-future": {
              "relativeTimePattern-count-one": "{0} жек. кейін",
              "relativeTimePattern-count-other": "{0} жек. кейін"
            },
            "relativeTime-type-past": {
              "relativeTimePattern-count-one": "{0} жек. бұрын",
              "relativeTimePattern-count-other": "{0} жек. бұрын"
            }
          },
          "sun-narrow": {
            "relative-type--1": "өткен жс",
            "relative-type-0": "осы жс",
            "relative-type-1": "келесі жс",
            "relativeTime-type-future": {
              "relativeTimePattern-count-one": "{0} жс кейін",
              "relativeTimePattern-count-other": "{0} жс кейін"
            },
            "relativeTime-type-past": {
              "relativeTimePattern-count-one": "{0} жс бұрын",
              "relativeTimePattern-count-other": "{0} жс бұрын"
            }
          },
          "mon": {
            "relative-type--1": "өткен дүйсенбі",
            "relative-type-0": "осы дүйсенбі",
            "relative-type-1": "келесі дүйсенбі",
            "relativeTime-type-future": {
              "relativeTimePattern-count-one": "{0} дүйсенбіден кейін",
              "relativeTimePattern-count-other": "{0} дүйсенбіден кейін"
            },
            "relativeTime-type-past": {
              "relativeTimePattern-count-one": "{0} дүйсенбі бұрын",
              "relativeTimePattern-count-other": "{0} дүйсенбі бұрын"
            }
          },
          "mon-short": {
            "relative-type--1": "өткен дүй.",
            "relative-type-0": "осы дүй.",
            "relative-type-1": "келесі дүй.",
            "relativeTime-type-future": {
              "relativeTimePattern-count-one": "{0} дүй. кейін",
              "relativeTimePattern-count-other": "{0} дүй. кейін"
            },
            "relativeTime-type-past": {
              "relativeTimePattern-count-one": "{0} дүй. бұрын",
              "relativeTimePattern-count-other": "{0} дүй. бұрын"
            }
          },
          "mon-narrow": {
            "relative-type--1": "өткен дс",
            "relative-type-0": "осы дс",
            "relative-type-1": "келесі дс",
            "relativeTime-type-future": {
              "relativeTimePattern-count-one": "{0} дс кейін",
              "relativeTimePattern-count-other": "{0} дс кейін"
            },
            "relativeTime-type-past": {
              "relativeTimePattern-count-one": "{0} дс бұрын",
              "relativeTimePattern-count-other": "{0} дс бұрын"
            }
          },
          "tue": {
            "relative-type--1": "өткен сейсенбі",
            "relative-type-0": "осы сейсенбі",
            "relative-type-1": "келесі сейсенбі",
            "relativeTime-type-future": {
              "relativeTimePattern-count-one": "{0} сейсенбіден кейін",
              "relativeTimePattern-count-other": "{0} сейсенбіден кейін"
            },
            "relativeTime-type-past": {
              "relativeTimePattern-count-one": "{0} сейсенбі бұрын",
              "relativeTimePattern-count-other": "{0} сейсенбі бұрын"
            }
          },
          "tue-short": {
            "relative-type--1": "өткен сей.",
            "relative-type-0": "осы сей.",
            "relative-type-1": "келесі сей.",
            "relativeTime-type-future": {
              "relativeTimePattern-count-one": "{0} сей. кейін",
              "relativeTimePattern-count-other": "{0} сей. кейін"
            },
            "relativeTime-type-past": {
              "relativeTimePattern-count-one": "{0} сей. бұрын",
              "relativeTimePattern-count-other": "{0} сей. бұрын"
            }
          },
          "tue-narrow": {
            "relative-type--1": "өткен сс",
            "relative-type-0": "осы сс",
            "relative-type-1": "келесі сс",
            "relativeTime-type-future": {
              "relativeTimePattern-count-one": "{0} сс кейін",
              "relativeTimePattern-count-other": "{0} сс кейін"
            },
            "relativeTime-type-past": {
              "relativeTimePattern-count-one": "{0} сс бұрын",
              "relativeTimePattern-count-other": "{0} сс бұрын"
            }
          },
          "wed": {
            "relative-type--1": "өткен сәрсенбі",
            "relative-type-0": "осы сәрсенбі",
            "relative-type-1": "келесі сәрсенбі",
            "relativeTime-type-future": {
              "relativeTimePattern-count-one": "{0} сәрсенбіден кейін",
              "relativeTimePattern-count-other": "{0} сәрсенбіден кейін"
            },
            "relativeTime-type-past": {
              "relativeTimePattern-count-one": "{0} сәрсенбі бұрын",
              "relativeTimePattern-count-other": "{0} сәрсенбі бұрын"
            }
          },
          "wed-short": {
            "relative-type--1": "өткен сәр.",
            "relative-type-0": "осы сәр.",
            "relative-type-1": "келесі сәр.",
            "relativeTime-type-future": {
              "relativeTimePattern-count-one": "{0} сәр. кейін",
              "relativeTimePattern-count-other": "{0} сәр. кейін"
            },
            "relativeTime-type-past": {
              "relativeTimePattern-count-one": "{0} сәр. бұрын",
              "relativeTimePattern-count-other": "{0} сәр. бұрын"
            }
          },
          "wed-narrow": {
            "relative-type--1": "өткен ср",
            "relative-type-0": "осы ср",
            "relative-type-1": "келесі ср",
            "relativeTime-type-future": {
              "relativeTimePattern-count-one": "{0} ср кейін",
              "relativeTimePattern-count-other": "{0} ср кейін"
            },
            "relativeTime-type-past": {
              "relativeTimePattern-count-one": "{0} ср бұрын",
              "relativeTimePattern-count-other": "{0} ср бұрын"
            }
          },
          "thu": {
            "relative-type--1": "өткен бейсенбі",
            "relative-type-0": "осы бейсенбі",
            "relative-type-1": "келесі бейсенбі",
            "relativeTime-type-future": {
              "relativeTimePattern-count-one": "{0} бейсенбіден кейін",
              "relativeTimePattern-count-other": "{0} бейсенбіден кейін"
            },
            "relativeTime-type-past": {
              "relativeTimePattern-count-one": "{0} бейсенбі бұрын",
              "relativeTimePattern-count-other": "{0} бейсенбі бұрын"
            }
          },
          "thu-short": {
            "relative-type--1": "өткен бей.",
            "relative-type-0": "осы бей.",
            "relative-type-1": "келесі бей.",
            "relativeTime-type-future": {
              "relativeTimePattern-count-one": "{0} бей. кейін",
              "relativeTimePattern-count-other": "{0} бей. кейін"
            },
            "relativeTime-type-past": {
              "relativeTimePattern-count-one": "{0} бей. бұрын",
              "relativeTimePattern-count-other": "{0} бей. бұрын"
            }
          },
          "thu-narrow": {
            "relative-type--1": "өткен бс",
            "relative-type-0": "осы бс",
            "relative-type-1": "келесі бс",
            "relativeTime-type-future": {
              "relativeTimePattern-count-one": "{0} бс кейін",
              "relativeTimePattern-count-other": "{0} бс кейін"
            },
            "relativeTime-type-past": {
              "relativeTimePattern-count-one": "{0} бс бұрын",
              "relativeTimePattern-count-other": "{0} бс бұрын"
            }
          },
          "fri": {
            "relative-type--1": "өткен жұма",
            "relative-type-0": "осы жұма",
            "relative-type-1": "келесі жұма",
            "relativeTime-type-future": {
              "relativeTimePattern-count-one": "{0} жұмадан кейін",
              "relativeTimePattern-count-other": "{0} жұмадан кейін"
            },
            "relativeTime-type-past": {
              "relativeTimePattern-count-one": "{0} жұма бұрын",
              "relativeTimePattern-count-other": "{0} жұма бұрын"
            }
          },
          "fri-short": {
            "relative-type--1": "өткен жұм.",
            "relative-type-0": "осы жұм.",
            "relative-type-1": "келесі жұм.",
            "relativeTime-type-future": {
              "relativeTimePattern-count-one": "{0} жұм. кейін",
              "relativeTimePattern-count-other": "{0} жұм. кейін"
            },
            "relativeTime-type-past": {
              "relativeTimePattern-count-one": "{0} жұм. бұрын",
              "relativeTimePattern-count-other": "{0} жұм. бұрын"
            }
          },
          "fri-narrow": {
            "relative-type--1": "өткен жм",
            "relative-type-0": "осы жм",
            "relative-type-1": "келесі жм",
            "relativeTime-type-future": {
              "relativeTimePattern-count-one": "{0} жм кейін",
              "relativeTimePattern-count-other": "{0} жм кейін"
            },
            "relativeTime-type-past": {
              "relativeTimePattern-count-one": "{0} жм бұрын",
              "relativeTimePattern-count-other": "{0} жм бұрын"
            }
          },
          "sat": {
            "relative-type--1": "өткен сенбі",
            "relative-type-0": "осы сенбі",
            "relative-type-1": "келесі сенбі",
            "relativeTime-type-future": {
              "relativeTimePattern-count-one": "{0} сенбіден кейін",
              "relativeTimePattern-count-other": "{0} сенбіден кейін"
            },
            "relativeTime-type-past": {
              "relativeTimePattern-count-one": "{0} сенбі бұрын",
              "relativeTimePattern-count-other": "{0} сенбі бұрын"
            }
          },
          "sat-short": {
            "relative-type--1": "өткен сен.",
            "relative-type-0": "осы сен.",
            "relative-type-1": "келесі сен.",
            "relativeTime-type-future": {
              "relativeTimePattern-count-one": "{0} сен. кейін",
              "relativeTimePattern-count-other": "{0} сен. кейін"
            },
            "relativeTime-type-past": {
              "relativeTimePattern-count-one": "{0} сен. бұрын",
              "relativeTimePattern-count-other": "{0} сен. бұрын"
            }
          },
          "sat-narrow": {
            "relative-type--1": "өткен сб",
            "relative-type-0": "осы сб",
            "relative-type-1": "келесі сб",
            "relativeTime-type-future": {
              "relativeTimePattern-count-one": "{0} сб кейін",
              "relativeTimePattern-count-other": "{0} сб кейін"
            },
            "relativeTime-type-past": {
              "relativeTimePattern-count-one": "{0} сб бұрын",
              "relativeTimePattern-count-other": "{0} сб бұрын"
            }
          },
          "dayperiod-short": {
            "displayName": "АМ/РМ"
          },
          "dayperiod": {
            "displayName": "АМ/РМ"
          },
          "dayperiod-narrow": {
            "displayName": "АМ/РМ"
          },
          "hour": {
            "displayName": "сағат",
            "relative-type-0": "осы сағат",
            "relativeTime-type-future": {
              "relativeTimePattern-count-one": "{0} сағаттан кейін",
              "relativeTimePattern-count-other": "{0} сағаттан кейін"
            },
            "relativeTime-type-past": {
              "relativeTimePattern-count-one": "{0} сағат бұрын",
              "relativeTimePattern-count-other": "{0} сағат бұрын"
            }
          },
          "hour-short": {
            "displayName": "сағ",
            "relative-type-0": "осы сағат",
            "relativeTime-type-future": {
              "relativeTimePattern-count-one": "{0} сағ. кейін",
              "relativeTimePattern-count-other": "{0} сағ. кейін"
            },
            "relativeTime-type-past": {
              "relativeTimePattern-count-one": "{0} сағ. бұрын",
              "relativeTimePattern-count-other": "{0} сағ. бұрын"
            }
          },
          "hour-narrow": {
            "displayName": "сағ",
            "relative-type-0": "осы сағат",
            "relativeTime-type-future": {
              "relativeTimePattern-count-one": "{0} сағ. кейін",
              "relativeTimePattern-count-other": "{0} сағ. кейін"
            },
            "relativeTime-type-past": {
              "relativeTimePattern-count-one": "{0} сағ. бұрын",
              "relativeTimePattern-count-other": "{0} сағ. бұрын"
            }
          },
          "minute": {
            "displayName": "минут",
            "relative-type-0": "осы минут",
            "relativeTime-type-future": {
              "relativeTimePattern-count-one": "{0} минуттан кейін",
              "relativeTimePattern-count-other": "{0} минуттан кейін"
            },
            "relativeTime-type-past": {
              "relativeTimePattern-count-one": "{0} минут бұрын",
              "relativeTimePattern-count-other": "{0} минут бұрын"
            }
          },
          "minute-short": {
            "displayName": "мин.",
            "relative-type-0": "осы минут",
            "relativeTime-type-future": {
              "relativeTimePattern-count-one": "{0} мин. кейін",
              "relativeTimePattern-count-other": "{0} мин. кейін"
            },
            "relativeTime-type-past": {
              "relativeTimePattern-count-one": "{0} мин. бұрын",
              "relativeTimePattern-count-other": "{0} мин. бұрын"
            }
          },
          "minute-narrow": {
            "displayName": "мин",
            "relative-type-0": "осы минут",
            "relativeTime-type-future": {
              "relativeTimePattern-count-one": "{0} мин. кейін",
              "relativeTimePattern-count-other": "{0} мин. кейін"
            },
            "relativeTime-type-past": {
              "relativeTimePattern-count-one": "{0} мин. бұрын",
              "relativeTimePattern-count-other": "{0} мин. бұрын"
            }
          },
          "second": {
            "displayName": "секунд",
            "relative-type-0": "қазір",
            "relativeTime-type-future": {
              "relativeTimePattern-count-one": "{0} секундтан кейін",
              "relativeTimePattern-count-other": "{0} секундтан кейін"
            },
            "relativeTime-type-past": {
              "relativeTimePattern-count-one": "{0} секунд бұрын",
              "relativeTimePattern-count-other": "{0} секунд бұрын"
            }
          },
          "second-short": {
            "displayName": "с",
            "relative-type-0": "қазір",
            "relativeTime-type-future": {
              "relativeTimePattern-count-one": "{0} сек. кейін",
              "relativeTimePattern-count-other": "{0} сек. кейін"
            },
            "relativeTime-type-past": {
              "relativeTimePattern-count-one": "{0} сек. бұрын",
              "relativeTimePattern-count-other": "{0} сек. бұрын"
            }
          },
          "second-narrow": {
            "displayName": "с",
            "relative-type-0": "қазір",
            "relativeTime-type-future": {
              "relativeTimePattern-count-one": "{0} сек. кейін",
              "relativeTimePattern-count-other": "{0} сек. кейін"
            },
            "relativeTime-type-past": {
              "relativeTimePattern-count-one": "{0} сек. бұрын",
              "relativeTimePattern-count-other": "{0} сек. бұрын"
            }
          },
          "zone": {
            "displayName": "уақыт белдеуі"
          },
          "zone-short": {
            "displayName": "уақ. белдеуі"
          },
          "zone-narrow": {
            "displayName": "уақ. белдеуі"
          }
        }
      }
    }
  }
}
