{
  "main": {
    "lrc": {
      "identity": {
        "version": {
          "_cldrVersion": "43"
        },
        "language": "lrc"
      },
      "localeDisplayNames": {
        "territories": {
          "001": "دونیا",
          "002": "ئفریقا",
          "003": "ئمریکا شومالی",
          "005": "ئمریکا ھارگە",
          "009": "ھوم پئڤأند جأھوٙن آڤ",
          "013": "مینجا ئمریکا",
          "019": "ئمریکا",
          "021": "ئمریکا ڤارو",
          "029": "کارائیب",
          "142": "آسیا",
          "150": "ئوروٙپا",
          "419": "ئمریکا لاتین",
          "BR": "بئرئزیل",
          "CN": "چین",
          "DE": "آلمان",
          "FR": "فأرانسە",
          "GB": "بیریتانیا گأپ",
          "GB-alt-short": "بیریتانیا گأپ",
          "IN": "ھئن",
          "IT": "ئیتالیا",
          "JP": "جاپوٙن",
          "RU": "روٙسیە",
          "US": "ڤولاتیا یأکاگئرتە",
          "US-alt-short": "ڤولاتیا یأکاگئرتە",
          "ZZ": "راساگە نادیار"
        }
      }
    }
  }
}
