{
  "main": {
    "gsw-FR": {
      "identity": {
        "version": {
          "_cldrVersion": "43"
        },
        "language": "gsw",
        "territory": "FR"
      },
      "localeDisplayNames": {
        "variants": {
          "1901": "Alti tüütschi Rächtschriibig",
          "1994": "Schtandardisierti Resianischi Rächtschriibig",
          "1996": "Nööi tüütschi Rächtschriibig",
          "1606NICT": "Schpaats Mittelfranzösisch",
          "AREVELA": "Oschtarmeenisch",
          "AREVMDA": "Weschtarmeenisch",
          "BAKU1926": "Äinheitlichs Türggischs Alfabeet",
          "BISKE": "Bela-Tialäkt",
          "BOONT": "Boontling",
          "FONIPA": "Foneetisch (IPA)",
          "FONUPA": "Foneetisch (UPA)",
          "LIPAW": "Lipowaz-Mundart",
          "MONOTON": "Monotonisch",
          "NEDIS": "Natisone-Mundart",
          "NJIVA": "Njiva-Mundart",
          "OSOJS": "Osojane-Mundart",
          "POLYTON": "Politonisch",
          "POSIX": "Posix",
          "REVISED": "Nööi Rächtschriibig",
          "ROZAJ": "Resianisch",
          "SAAHO": "Saho",
          "SCOTLAND": "Schottischs Schtandardänglisch",
          "SCOUSE": "Scouse-Mundart",
          "SOLBA": "Solbica-Mundart",
          "TARASK": "Taraskievica-Rächtschriibig"
        }
      }
    }
  }
}
