{
  "main": {
    "xog": {
      "identity": {
        "version": {
          "_cldrVersion": "38"
        },
        "language": "xog"
      },
      "localeDisplayNames": {
        "territories": {
          "001": "001",
          "002": "002",
          "003": "003",
          "005": "005",
          "009": "009",
          "011": "011",
          "013": "013",
          "014": "014",
          "015": "015",
          "017": "017",
          "018": "018",
          "019": "019",
          "021": "021",
          "029": "029",
          "030": "030",
          "034": "034",
          "035": "035",
          "039": "039",
          "053": "053",
          "054": "054",
          "057": "057",
          "061": "061",
          "142": "142",
          "143": "143",
          "145": "145",
          "150": "150",
          "151": "151",
          "154": "154",
          "155": "155",
          "202": "202",
          "419": "419",
          "AC": "AC",
          "AD": "Andora",
          "AE": "Emireeti",
          "AF": "Afaganisitani",
          "AG": "Antigwa ni Barabuda",
          "AI": "Angwila",
          "AL": "Alibaniya",
          "AM": "Arameniya",
          "AO": "Angola",
          "AQ": "AQ",
          "AR": "Arigentina",
          "AS": "Samowa omumerika",
          "AT": "Awusituriya",
          "AU": "Awusitureliya",
          "AW": "Aruba",
          "AX": "AX",
          "AZ": "Azerebayijaani",
          "BA": "Boziniya Hezegovina",
          "BB": "Barabadosi",
          "BD": "Bangaladesi",
          "BE": "Bubirigi",
          "BF": "Burukina Faso",
          "BG": "Bulugariya",
          "BH": "Baareeni",
          "BI": "Burundi",
          "BJ": "Benini",
          "BL": "BL",
          "BM": "Beremuda",
          "BN": "Burunayi",
          "BO": "Boliviya",
          "BQ": "BQ",
          "BR": "Buraziiri",
          "BS": "Bahamasi",
          "BT": "Butaani",
          "BV": "BV",
          "BW": "Botiswana",
          "BY": "Belarusi",
          "BZ": "Belize",
          "CA": "Kanada",
          "CC": "CC",
          "CD": "Kongo - Zayire",
          "CD-alt-variant": "Kongo - Zayire",
          "CF": "Lipabulika ya Senturafiriki",
          "CG": "Kongo",
          "CG-alt-variant": "Kongo",
          "CH": "Switizirandi",
          "CI": "Kote Divwa",
          "CI-alt-variant": "Kote Divwa",
          "CK": "Ebizinga bya Kkuki",
          "CL": "Cile",
          "CM": "Kameruuni",
          "CN": "Cayina",
          "CO": "Kolombya",
          "CP": "CP",
          "CR": "Kosita Rika",
          "CU": "Cuba",
          "CV": "Ebizinga bya Kepu Veredi",
          "CW": "CW",
          "CX": "CX",
          "CY": "Sipuriya",
          "CZ": "Lipabulika ya Ceeka",
          "CZ-alt-variant": "Lipabulika ya Ceeka",
          "DE": "Budaaki",
          "DG": "DG",
          "DJ": "Jjibuti",
          "DK": "Denimaaka",
          "DM": "Dominika",
          "DO": "Lipabulika ya Dominika",
          "DZ": "Aligerya",
          "EA": "EA",
          "EC": "Ekwado",
          "EE": "Esitoniya",
          "EG": "Misiri",
          "EH": "EH",
          "ER": "Eritureya",
          "ES": "Sipeyini",
          "ET": "Esyopya",
          "EU": "EU",
          "EZ": "EZ",
          "FI": "Finilandi",
          "FJ": "Fiji",
          "FK": "Ebiizinga bya Falikalandi",
          "FK-alt-variant": "Ebiizinga bya Falikalandi",
          "FM": "Mikuronezya",
          "FO": "FO",
          "FR": "Bufalansa",
          "GA": "Gaboni",
          "GB": "Bungereza",
          "GB-alt-short": "Bungereza",
          "GD": "Gurenada",
          "GE": "Gyogya",
          "GF": "Guyana enfalansa",
          "GG": "GG",
          "GH": "Gana",
          "GI": "Giburalita",
          "GL": "Gurenelandi",
          "GM": "Gambya",
          "GN": "Gini",
          "GP": "Gwadalupe",
          "GQ": "Gayana yaku ekweta",
          "GR": "Buyonaani",
          "GS": "GS",
          "GT": "Gwatemala",
          "GU": "Gwamu",
          "GW": "Gini-Bisawu",
          "GY": "Gayana",
          "HK": "HK",
          "HK-alt-short": "HK",
          "HM": "HM",
          "HN": "Hundurasi",
          "HR": "Kurowesya",
          "HT": "Hayiti",
          "HU": "Hangare",
          "IC": "IC",
          "ID": "Yindonezya",
          "IE": "Ayalandi",
          "IL": "Yisirayeri",
          "IM": "IM",
          "IN": "Buyindi",
          "IO": "Ebizinga bya Cago",
          "IQ": "Yiraaka",
          "IR": "Yiraani",
          "IS": "Ayisirandi",
          "IT": "Yitale",
          "JE": "JE",
          "JM": "Jamayika",
          "JO": "Yorodani",
          "JP": "Japani",
          "KE": "Kenya",
          "KG": "Kirigizisitaani",
          "KH": "Kambodya",
          "KI": "Kiribati",
          "KM": "Ebizinga bya Komoro",
          "KN": "Senti Kitisi ne Nevisi",
          "KP": "Koreya eya mumambuka",
          "KR": "Koreya eya mumaserengeta",
          "KW": "Kuweti",
          "KY": "Ebizinga bya Kayimaani",
          "KZ": "Kazakisitaani",
          "LA": "Lawosi",
          "LB": "Lebanoni",
          "LC": "Senti Luciya",
          "LI": "Licitensitayini",
          "LK": "Sirilanka",
          "LR": "Liberya",
          "LS": "Lesoso",
          "LT": "Lisuwenya",
          "LU": "Lukisembaaga",
          "LV": "Lativya",
          "LY": "Libya",
          "MA": "Moroko",
          "MC": "Monako",
          "MD": "Molodova",
          "ME": "ME",
          "MF": "MF",
          "MG": "Madagasika",
          "MH": "Bizinga bya Mariso",
          "MK": "MK",
          "ML": "Mali",
          "MM": "Myanima",
          "MN": "Mongoliya",
          "MO": "MO",
          "MO-alt-short": "MO",
          "MP": "Bizinga bya Mariyana ebyamumambuka",
          "MQ": "Maritiniiki",
          "MR": "Mawulitenya",
          "MS": "Monteseraati",
          "MT": "Malita",
          "MU": "Mawulisyasi",
          "MV": "Ebizinga bya Malidive",
          "MW": "Malawi",
          "MX": "Mekisiko",
          "MY": "Malezya",
          "MZ": "Mozambiiki",
          "NA": "Namibiya",
          "NC": "Kaledonya mupya",
          "NE": "Nije",
          "NF": "Kizinga ky’eNorofoko",
          "NG": "Nayijerya",
          "NI": "Nikaraguwa",
          "NL": "Holandi",
          "NO": "Nowe",
          "NP": "Nepalo",
          "NR": "Nawuru",
          "NU": "Niyuwe",
          "NZ": "Niyuziirandi",
          "OM": "Omaani",
          "PA": "Panama",
          "PE": "Peru",
          "PF": "Polinesiya enfalansa",
          "PG": "Papwa Nyugini",
          "PH": "Ebizinga bya Firipino",
          "PK": "Pakisitaani",
          "PL": "Polandi",
          "PM": "Senti Piyere ni Mikeloni",
          "PN": "Pitikeeni",
          "PR": "Potoriko",
          "PS": "Palesitayini ni Gaza",
          "PS-alt-short": "Palesitayini ni Gaza",
          "PT": "Potugaali",
          "PW": "Palawu",
          "PY": "Paragwayi",
          "QA": "Kataa",
          "QO": "QO",
          "RE": "Leyunyoni",
          "RO": "Lomaniya",
          "RS": "RS",
          "RU": "Lasa",
          "RW": "Rwanda",
          "SA": "Sawudarebya",
          "SB": "Ebizanga bya Solomooni",
          "SC": "Sesere",
          "SD": "Sudaani",
          "SE": "Swideni",
          "SG": "Singapowa",
          "SH": "Senti Herena",
          "SI": "Sirovenya",
          "SJ": "SJ",
          "SK": "Sirovakya",
          "SL": "Siyeralewone",
          "SM": "Sanimarino",
          "SN": "Senegaalo",
          "SO": "Somaliya",
          "SR": "Surinaamu",
          "SS": "SS",
          "ST": "Sanitome ni Purincipe",
          "SV": "El salivado",
          "SX": "SX",
          "SY": "Siriya",
          "SZ": "Swazirandi",
          "SZ-alt-variant": "Swazirandi",
          "TA": "TA",
          "TC": "Ebizinga bya Taaka ni Kayikosi",
          "TD": "Caadi",
          "TF": "TF",
          "TG": "Togo",
          "TH": "Tayirandi",
          "TJ": "Tajikisitaani",
          "TK": "Tokelawu",
          "TL": "Timowa",
          "TL-alt-variant": "Timowa",
          "TM": "Takimenesitaani",
          "TN": "Tunisya",
          "TO": "Tonga",
          "TR": "Ttake",
          "TT": "Turindaadi ni Tobago",
          "TV": "Tuvalu",
          "TW": "Tayiwani",
          "TZ": "TZ",
          "UA": "Yukurayine",
          "UG": "Yuganda",
          "UM": "UM",
          "UN": "UN",
          "US": "Amerika",
          "US-alt-short": "Amerika",
          "UY": "Wurugwayi",
          "UZ": "Wuzibekisitaani",
          "VA": "Vatikaani",
          "VC": "Senti Vinsenti ni Gurendadiini",
          "VE": "Venzwera",
          "VG": "Ebizinga bya Virigini ebitwalibwa Bungereza",
          "VI": "Ebizinga bya Virigini eby’Amerika",
          "VN": "Vyetinaamu",
          "VU": "Vanawuwatu",
          "WF": "Walisi ni Futuna",
          "WS": "Samowa",
          "XA": "XA",
          "XB": "XB",
          "XK": "XK",
          "YE": "Yemeni",
          "YT": "Mayotte",
          "ZA": "Sawusafirika",
          "ZM": "Zambya",
          "ZW": "Zimbabwe",
          "ZZ": "ZZ"
        }
      }
    }
  }
}
