{
  "main": {
    "th": {
      "identity": {
        "version": {
          "_cldrVersion": "41"
        },
        "language": "th"
      },
      "typographicNames": {
        "axisNames": {
          "ital": "ตัวเอียง",
          "opsz": "ขนาดปรับอัตโนมัติ",
          "slnt": "เอียง",
          "wdth": "ความกว้าง",
          "wght": "ความหนา"
        },
        "styleNames": {
          "ital-subtype-1": "เล่นหาง",
          "opsz-subtype-8": "คำอธิบายภาพ",
          "opsz-subtype-12": "ข้อความ",
          "opsz-subtype-18": "ตัวพิมพ์ใหญ่",
          "opsz-subtype-72": "การแสดงผล",
          "opsz-subtype-144": "รูปโปสเตอร์",
          "slnt-subtype--12": "เอนหลัง",
          "slnt-subtype-0": "ตั้งตรง",
          "slnt-subtype-12": "เอน",
          "slnt-subtype-24": "เอนพิเศษ",
          "wdth-subtype-50": "บีบมากที่สุด",
          "wdth-subtype-50-alt-compressed": "บีบอัดมากที่สุด",
          "wdth-subtype-50-alt-narrow": "แคบมากที่สุด",
          "wdth-subtype-62.5": "บีบพิเศษ",
          "wdth-subtype-62.5-alt-compressed": "บีบอัดพิเศษ",
          "wdth-subtype-62.5-alt-narrow": "แคบพิเศษ",
          "wdth-subtype-75": "บีบ",
          "wdth-subtype-75-alt-compressed": "บีบอัด",
          "wdth-subtype-75-alt-narrow": "แบบแคบ",
          "wdth-subtype-87.5": "กึ่งบีบ",
          "wdth-subtype-87.5-alt-compressed": "กึ่งบีบอัด",
          "wdth-subtype-87.5-alt-narrow": "กึ่งแคบ",
          "wdth-subtype-100": "ปกติ",
          "wdth-subtype-112.5": "กึ่งขยาย",
          "wdth-subtype-112.5-alt-extended": "กึ่งเสริม",
          "wdth-subtype-112.5-alt-wide": "กึ่งกว้าง",
          "wdth-subtype-125": "ขยายแล้ว",
          "wdth-subtype-125-alt-extended": "แบบขยาย",
          "wdth-subtype-125-alt-wide": "กว้าง",
          "wdth-subtype-150": "ขยายพิเศษ",
          "wdth-subtype-150-alt-extended": "เสริมพิเศษ",
          "wdth-subtype-150-alt-wide": "กว้างพิเศษ",
          "wdth-subtype-200": "ขยายมากที่สุด",
          "wdth-subtype-200-alt-extended": "เสริมมากที่สุด",
          "wdth-subtype-200-alt-wide": "กว้างมากที่สุด",
          "wght-subtype-100": "ผอม",
          "wght-subtype-200": "บางพิเศษ",
          "wght-subtype-200-alt-ultra": "บางมากที่สุด",
          "wght-subtype-300": "บาง",
          "wght-subtype-350": "กึ่งบาง",
          "wght-subtype-380": "หนังสือ",
          "wght-subtype-400": "ความเข้มปกติ",
          "wght-subtype-500": "ปานกลาง",
          "wght-subtype-600": "กึ่งหนา",
          "wght-subtype-600-alt-demi": "หนาปานกลาง",
          "wght-subtype-700": "หนา",
          "wght-subtype-800": "หนาพิเศษ",
          "wght-subtype-800-alt-ultra": "หนามากที่สุด",
          "wght-subtype-900": "ดำ",
          "wght-subtype-900-alt-heavy": "หนัก",
          "wght-subtype-950": "ดำพิเศษ",
          "wght-subtype-950-alt-ultrablack": "ดำมากที่สุด",
          "wght-subtype-950-alt-ultraheavy": "หนักมากที่สุด"
        },
        "featureNames": {
          "afrc": "เศษส่วนแนวตั้ง",
          "cpsp": "ระยะห่างตัวพิมพ์ใหญ่",
          "dlig": "ลิเกเจอร์ทางเลือก",
          "frac": "เศษส่วนทแยงมุม",
          "lnum": "ตัวเลขบนเส้นบรรทัด",
          "onum": "ตัวเลขลักษณะเก่า",
          "ordn": "ตัวเลขบริบท",
          "pnum": "ตัวเลขแบบสัดส่วน",
          "smcp": "ตัวพิมพ์ใหญ่แบบเล็ก",
          "smcp-alt-short": "ตัวพิมพ์ใหญ่เล็ก",
          "tnum": "ตัวเลขแบบตาราง",
          "zero": "เลขศูนย์เอียง"
        }
      }
    }
  }
}
